{
 "mdsDat": {
 "x": [ -0.12409, 0.24991, -0.20374, -0.13745, -0.092707, -0.11093, 0.26708, 0.15192 ],
"y": [ -0.085209, 0.1003, 0.21945, 0.26049, -0.24624, -0.22479, 0.006543, -0.030529 ],
"topics": [ 1, 2, 3, 4, 5, 6, 7, 8 ],
"Freq": [ 18.197, 14.904, 13.103, 12.729, 11.637,  10.31, 10.189, 8.9308 ],
"cluster": [      1,      1,      1,      1,      1,      1,      1,      1 ] 
},
"tinfo": {
 "Term": [ "love", "follow", "just", "like", "get", "please", "followmejosh", "dont", "new", "can", "one", "will", "now", "people", "make", "see", "want", "day", "today", "best", "happy", "know", "good", "time", "video", "via", "birthday", "got", "much", "josh", "biscuits", "jabberduck", "nsfw", "code", "adult", "fav", "ebay", "full", "discount", "read", "porn", "black", "sale", "use", "vintage", "cute", "dress", "size", "weather", "job", "hair", "sexy", "yes", "wear", "texting", "april", "mom", "mood", "high", "president", "followtrick", "mgwv", "followback", "teamfollowback", "amo", "followmejosh", "follow", "josh", "hii", "gain", "brazil", "love", "dream", "ilysm", "hey", "harry", "pls", "drummer", "good", "baby", "loves", "ily", "cant", "mind", "babe", "hello", "wait", "true", "follows", "morning", "time", "life", "back", "never", "soon", "first", "pretty", "coming", "every", "done", "friends", "end", "start", "sorry", "long", "many", "weekend", "senior", "sure", "save", "story", "waiting", "snapchat", "couldnt", "without", "ways", "text", "change", "comes", "click", "pal", "mate", "birthday", "dont", "want", "know", "really", "lol", "fuck", "say", "hate", "girl", "bad", "tell", "stop", "care", "fake", "nothing", "home", "waste", "wish", "art", "nice", "ask", "try", "wrong", "understand", "talking", "truth", "anything", "unfollower", "unfollowed", "automatically", "opens", "follower", "unfollowers", "checked", "stats", "via", "today", "one", "posted", "now", "followers", "followed", "right", "watch", "new", "day", "excited", "facebook", "song", "beautiful", "wow", "shots", "york", "found", "park", "gonna", "single", "heroprinceofpop", "gameinsight", "shot", "get", "check", "thanks", "night", "profile", "friday", "ready", "next", "live", "last", "week", "show", "party", "music", "nowplaying", "gold", "working", "hot", "pool", "ipad", "issue", "deals", "dead", "set", "watching", "car", "date", "httptcoxhrka1pcje", "laughted", "coffin", "caught", "like", "inside", "couple", "bruce", "best", "sex", "got", "ever", "still", "goals", "going", "way", "better", "looking", "even", "friend", "looks", "jenner", "years", "find", "htt", "relationship", "didnt", "though", "history", "already", "rumor", "spread", "liked", "seen", "will", "sad", "god", "thank", "think", "makes", "game", "always", "free", "give", "tomorrow", "tweet", "win", "social", "help", "everything", "greysanatomy", "things", "fans", "media", "sleep", "remember", "join", "hand", "road", "anyone", "shit", "real", "big", "man", "getting", "little", "may", "fucking", "girls", "said", "keep", "work", "play", "two", "school", "old", "top", "omg", "yeah", "please", "tonight", "following", "days", "hope", "call", "nigga", "lmao", "funny", "proud", "gotta", "see", "come", "someone", "look", "take", "wanna", "everyone", "something", "thing", "let", "stay", "fun", "can", "people", "year", "doesnt", "money", "put", "cause", "photo", "just", "make", "person", "amazing", "haha", "post", "kids", "guys", "twitter", "ass", "talk", "hard", "smile", "awesome", "around", "left", "hit", "crazy", "boy", "face", "feel", "mean", "yall", "heart", "making", "place", "head", "actually", "world", "support", "fan", "bed", "happen", "need", "made", "2015", "app", "happy", "video", "retweet", "trying", "together", "much", "great", "much", "miss", "lot", "great" ],
"logprob": [     30,     29,     28,     27,     26,     25,     24,     23,     22,     21,     20,     19,     18,     17,     16,     15,     14,     13,     12,     11,     10,      9,      8,      7,      6,      5,      4,      3,      2,      1, -5.5999, -6.4488, -5.3759, -5.1715, -5.3322, -4.2455, -5.5068, -4.4875, -6.2257, -4.3913, -5.0437, -4.7323, -5.1013, -4.5409, -6.0289, -4.8157, -5.5724, -6.0802, -5.614, -5.0122, -4.9185, -5.5282, -4.8952, -5.1654, -6.3456, -5.2938, -4.9993, -5.8115, -5.1358, -6.0727, -5.3946, -5.0324, -5.5362, -5.8416, -5.7291, -2.5145, -2.0728, -3.3448, -5.4629, -5.0869, -5.0254, -1.9882, -4.2726, -5.2979, -3.7985, -4.4493, -4.4855, -5.2441, -3.1458, -4.3079, -4.8085, -5.4849, -3.4744, -4.3844, -5.2888, -5.1484, -4.4454, -4.6592, -5.4361, -4.8578, -3.1574, -3.3993, -3.3707, -3.4641, -4.517, -3.8456, -4.4319, -4.5636, -4.0458, -4.4701, -4.2886, -4.4254, -4.5636, -4.5437, -4.589, -4.2275, -4.517, -5.6902, -4.3235, -5.3515, -5.1076, -4.9553, -5.7543, -5.2077, -4.8265, -5.6448, -5.2125, -4.8802, -5.3351, -5.3683, -4.3715, -4.2865, -3.2039, -2.5158, -2.9026, -3.0489, -3.4262, -3.5649, -3.7772, -3.8014, -4.2398, -3.8388, -4.2865, -4.2687, -3.899, -4.5486, -5.3197, -4.378, -4.1202, -5.7364, -4.3889, -4.9737, -4.325, -4.9161, -4.5206, -4.9236, -5.3197, -4.8794, -5.5303, -4.8651, -5.0371, -5.8504, -5.3123, -5.3375, -5.0185, -4.613, -5.2289, -4.1438, -3.1062, -2.8778, -2.4857, -4.9341, -2.6461, -4.017, -4.2801, -3.4118, -3.3638, -2.4571, -2.8676, -4.3583, -5.0092, -4.3487, -4.1811, -4.7953, -5.4959, -5.7786, -4.8369, -5.2347, -4.1227, -4.9131, -5.5261, -5.3557, -4.6738, -2.1927, -3.6149, -3.4108, -3.5904, -5.0661, -4.1532, -4.2874, -3.7197, -3.7598, -3.6605, -3.8417, -3.845, -4.4305, -4.0449, -5.3557, -5.0386, -4.5564, -4.2398, -5.6091, -5.3707, -5.0065, -5.0774, -5.0332, -4.7083, -4.7083, -4.6814, -4.8922, -5.5502, -5.1667, -5.1604, -4.7176, -2.0232, -4.567,  -4.67, -5.1796, -2.8108, -4.1995, -3.0233, -3.2136, -3.4073, -4.8523, -3.2896, -3.5259, -3.695, -4.1732, -3.5371, -4.229, -4.1732, -5.3478, -4.1027, -4.0004, -4.4453, -5.1667, -4.1408, -4.6856, -5.2394, -4.3622, -3.7259, -3.628, -4.3876, -3.3615, -2.3957, -3.7066, -3.5763, -3.0257, -3.0698, -3.7402, -3.5171, -3.2226, -3.3902, -3.5825, -3.7825, -3.9584, -3.7584, -5.0111, -3.9949, -3.6624, -5.257, -3.7366, -4.4589, -5.024, -4.3148, -4.3341, -4.6583, -5.0371, -5.316, -4.2088,  -4.08, -4.5376, -4.6145, -4.3718, -4.6516, -4.6626, -4.6538, -4.7168, -4.6831, -4.7911, -4.8057, -4.502, -4.8248, -4.8595, -4.952, -4.9645, -5.0226, -5.0517, -5.0598, -2.4463, -3.7985, -4.4415, -4.4474, -3.6522, -4.8199, -4.9381, -4.9575, -4.9841, -5.0289, -5.102, -2.897, -3.7679, -3.8003, -3.7707, -3.7055, -3.9076, -4.058, -4.1236, -4.3283, -4.1744, -4.6126, -4.6285, -2.5313, -2.801, -4.3291, -4.3522, -4.4157, -4.7835, -4.8303, -4.3428, -2.1138, -2.7942, -3.8698, -3.9918, -4.8488, -5.061, -5.131, -3.6605, -3.9258, -3.9997, -4.2571, -4.2284, -4.3591, -4.4305, -4.4637, -4.5268, -4.6152, -4.6404, -4.644, -4.689, -3.7187, -3.686, -4.2568, -4.3203, -4.4453, -4.6062, -4.6172, -4.4267, -3.1741, -4.5435, -4.6903, -4.7577, -4.8299, -3.7968, -4.786, -4.9059, -5.0637, -2.9623, -2.8215, -4.2497, -4.6106, -4.711, -3.4276, -3.623, -3.6754, -4.8881, -4.8131, -4.4823 ],
"loglift": [     30,     29,     28,     27,     26,     25,     24,     23,     22,     21,     20,     19,     18,     17,     16,     15,     14,     13,     12,     11,     10,      9,      8,      7,      6,      5,      4,      3,      2,      1,  1.601,  1.601,  1.601,  1.601,  1.601,  1.601,  1.601,  1.601,  1.601,  1.601,  1.601,  1.601,  1.601,  1.601,  1.601,  1.601,  1.601,  1.601,  1.601,  1.601,  1.601,  1.601,  1.601,  1.601,  1.601,  1.601,  1.601,  1.601,  1.601,  1.601, 1.8937, 1.8937, 1.8937, 1.8937, 1.8937, 1.8937, 1.8937, 1.8937, 1.8937, 1.8937, 1.8937, 1.8937, 1.8937, 1.8937, 1.8937, 1.8937, 1.8937, 1.8937, 1.8937, 1.8937, 1.8937, 1.8937, 1.8937, 1.8937, 1.8937, 1.8937, 1.8937, 1.8937, 1.8937, 1.8937, 2.0215, 2.0215, 2.0215, 2.0215, 2.0215, 2.0215, 2.0215, 2.0215, 2.0215, 2.0215, 2.0215, 2.0215, 2.0215, 2.0215, 2.0215, 2.0215, 2.0215, 2.0215, 2.0215, 2.0215, 2.0215, 2.0215, 2.0215, 2.0215, 2.0215, 2.0215, 2.0215, 2.0215, 2.0215, 2.0215, 2.0645, 2.0645, 2.0645, 2.0645, 2.0645, 2.0645, 2.0645, 2.0645, 2.0645, 2.0645, 2.0645, 2.0645, 2.0645, 2.0645, 2.0645, 2.0645, 2.0645, 2.0645, 2.0645, 2.0645, 2.0645, 2.0645, 2.0645, 2.0645, 2.0645, 2.0645, 2.0645, 2.0645, 2.0645, 2.0645, 2.1778, 2.1778, 2.1778, 2.1778, 2.1778, 2.1778, 2.1778, 2.1778, 2.1778, 2.1778, 2.1778, 2.1778, 2.1778, 2.1778, 2.1778, 2.1778, 2.1778, 2.1778, 2.1778, 2.1778, 2.1778, 2.1778, 2.1778, 2.1778, 2.1778, 2.1778, 2.1778, 2.1778, 2.1778, 2.1778, 2.3181, 2.3181, 2.3181, 2.3181, 2.3181, 2.3181, 2.3181, 2.3181, 2.3181, 2.3181, 2.3181, 2.3181, 2.3181, 2.3181, 2.3181, 2.3181, 2.3181, 2.3181, 2.3181, 2.3181, 2.3181, 2.3181, 2.3181, 2.3181, 2.3181, 2.3181, 2.3181, 2.3181, 2.3181, 2.3181, 2.3486, 2.3486, 2.3486, 2.3486, 2.3486, 2.3486, 2.3486, 2.3486, 2.3486, 2.3486, 2.3486, 2.3486, 2.3486, 2.3486, 2.3486, 2.3486, 2.3486, 2.3486, 2.3486, 2.3486, 2.3486, 2.3486, 2.3486, 2.3486, 2.3486, 2.3486, 2.3486, 2.3486, 2.3486, 2.3486, 2.5106, 2.5106, 2.5106, 2.5106, 2.5106, 2.5106, 2.5106, 2.5106, 2.5106, 2.5106, 2.5106, 2.5106, 2.5106, 2.5106, 2.5106, 2.5106, 2.5106, 2.5106, 2.5106, 2.5106, 2.5106, 2.5106, 2.5106, 2.5106, 2.5106, 2.5106, 2.5106, 2.5106, 2.5106, 2.5106,  1.601,  1.601,  1.601, 1.5985,  1.601, 1.6009, 1.6006,  1.601, 1.6006, 1.6004, 1.6005, 1.5972, 1.6005, 1.6006,  1.601, 1.6007,  1.601,  1.601,  1.601,  1.883, 1.8937, 1.8937, 1.8937, 1.8824, 1.8937, 1.8937, 1.8937, 1.8937, 1.8937, 1.8937, 2.0215, 2.0215, 2.0213,  2.021, 2.0202, 2.0215, 2.0213, 2.0215, 2.0207, 2.0171, 2.0214, 2.0215, 2.0637, 2.0645, 2.0645, 2.0645, 2.0645, 2.0645, 2.0645, 2.0591, 2.1778,  2.177, 2.1768, 2.1778, 2.1776, 2.1778, 2.1778, 2.3181, 2.3179,  2.318, 2.3181, 2.3173, 2.3181,  2.318, 2.3179, 2.3179, 2.3181, 2.3181, 2.3181, 2.3181, 2.3486, 2.3474, 2.3486, 2.3486, 2.3486, 2.3486, 2.3486, 2.3458, 2.5079, 2.5106, 2.5106, 2.5106, 2.5106, 1.5826, 1.5952, 1.5972, 2.1751, 1.9803, 2.4177, 1.8449, 2.0182, 2.3472, 1.4914, 1.6811, 1.2436, 1.4258, 1.4931, 0.8217 ],
"Freq": [   5941,   5459,   3944,   3640,   3168,   3798,   3510,   2955,   2798,   2912,   2719,   2133,   2316,   2222,   1999,   2107,   2007,   1856,   1837,   1656,   2057,   1734,   1867,   1624,   1529,   1462,   1485,   1339,   2106,   1530,    215, 91.999,    269,    330,    281,    833,    236,    654,    115,    720,    375,    512,    354,    620,    140,    471,    221,    133,    212,    387,    425,    231,    435,    332,    102,    292,    392,    174,    342,    134,    197,    283,    171,    126,    141,   3510,   5459,   1530,    184,    268,    285,   5941,    605,    217,    972,    507,    489,    229,   1867,    584,    354,    180,   1344,    541,    219,    252,    509,    411,    189,    337,   1624,   1275,   1312,   1195,    417,    816,    454,    398,    668,    437,    524,    457,    398,    406,    388,    557,    417,    129,    506,    181,    231,    269,    121,    209,    306,    135,    208,    290,    184,    178,    462,    503,   1485,   2955,   2007,   1734,   1189,   1035,    837,    817,    527,    787,    503,    512,    741,    387,    179,    459,    594,    118,    454,    253,    484,    268,    398,    266,    179,    278,    145,    282,    212, 93.999,    161,    157,    216,    324,    175,    518,   1462,   1837,   2719,    235,   2316,    588,    452,   1077,   1130,   2798,   1856,    418,    218,    422,    499,    270,    134,    101,    259,    174,    529,    240,    113,    134,    265,   3168,    764,    937,    783,    179,    446,    390,    688,    661,    730,    609,    607,    338,    497,    134,    184,    298,    409,    104,    132,    190,    177,    185,    256,    256,    263,    213,    107,    157,    158,    246,   3640,    286,    258,    155,   1656,    413,   1339,   1107,    912,    215,   1026,    810,    684,    424,    801,    401,    424,    131,    455,    504,    323,    157,    438,    254,    146,    351,    564,    622,    291,    812,   2133,    575,    655,   1136,   1087,    556,    695,    933,    789,    651,    533,    447,    546,    156,    431,    601,    122,    558,    271,    154,    313,    307,    222,    152,    115,    348, 982.98,    622, 575.99, 733.84, 554.99, 548.94, 553.75, 519.98, 537.77, 482.69, 475.73, 644.33, 466.71,  450.8,    411, 405.87, 382.99,    372,    369, 3753.1,    972,    511,    508,   1125,    350,    311,    305,    297,    284, 263.98,   2107, 881.96, 853.82, 879.49, 938.77, 766.99, 659.85, 617.99, 503.56, 587.34, 378.96, 372.99, 2909.5, 2221.8,    482,    471,    442,    306,    292, 475.36,   3944, 1997.4, 681.23,    603, 255.92,    207,    193,    730, 559.91, 519.99,    402, 413.74,    363, 337.99, 326.94, 306.96,    281,    274,    273,    261, 667.99, 690.23,    390,    366,    323,    275,    272,  329.2, 979.39,    249,    215,    201,    187, 1302.2,  484.8, 430.12, 206.43, 1892.8,   1397, 615.77, 379.65, 247.67, 1373.3, 1015.3, 732.73, 430.67,  343.6, 417.66 ],
"Total": [   5941,   5459,   3944,   3640,   3168,   3798,   3510,   2955,   2798,   2912,   2719,   2133,   2316,   2222,   1999,   2107,   2007,   1856,   1837,   1656,   2057,   1734,   1867,   1624,   1529,   1462,   1485,   1339,   2106,   1530,    215,     92,    269,    330,    281,    833,    236,    654,    115,    720,    375,    512,    354,    620,    140,    471,    221,    133,    212,    387,    425,    231,    435,    332,    102,    292,    392,    174,    342,    134,    197,    283,    171,    126,    141,   3510,   5459,   1530,    184,    268,    285,   5941,    605,    217,    972,    507,    489,    229,   1867,    584,    354,    180,   1344,    541,    219,    252,    509,    411,    189,    337,   1624,   1275,   1312,   1195,    417,    816,    454,    398,    668,    437,    524,    457,    398,    406,    388,    557,    417,    129,    506,    181,    231,    269,    121,    209,    306,    135,    208,    290,    184,    178,    462,    503,   1485,   2955,   2007,   1734,   1189,   1035,    837,    817,    527,    787,    503,    512,    741,    387,    179,    459,    594,    118,    454,    253,    484,    268,    398,    266,    179,    278,    145,    282,    212,     94,    161,    157,    216,    324,    175,    518,   1462,   1837,   2719,    235,   2316,    588,    452,   1077,   1130,   2798,   1856,    418,    218,    422,    499,    270,    134,    101,    259,    174,    529,    240,    113,    134,    265,   3168,    764,    937,    783,    179,    446,    390,    688,    661,    730,    609,    607,    338,    497,    134,    184,    298,    409,    104,    132,    190,    177,    185,    256,    256,    263,    213,    107,    157,    158,    246,   3640,    286,    258,    155,   1656,    413,   1339,   1107,    912,    215,   1026,    810,    684,    424,    801,    401,    424,    131,    455,    504,    323,    157,    438,    254,    146,    351,    564,    622,    291,    812,   2133,    575,    655,   1136,   1087,    556,    695,    933,    789,    651,    533,    447,    546,    156,    431,    601,    122,    558,    271,    154,    313,    307,    222,    152,    115,    348,    983,    622,    576,    736,    555,    549,    554,    520,    538,    483,    476,    647,    467,    451,    411,    406,    383,    372,    369,   3798,    972,    511,    508,   1138,    350,    311,    305,    297,    284,    264,   2107,    882,    854,    880,    940,    767,    660,    618,    504,    590,    379,    373,   2912,   2222,    482,    471,    442,    306,    292,    478,   3944,   1999,    682,    603,    256,    207,    193,    730,    560,    520,    402,    414,    363,    338,    327,    307,    281,    274,    273,    261,    668,    691,    390,    366,    323,    275,    272,    330,    982,    249,    215,    201,    187,   1329,    488,    432,    207,   2057,   1529,    650,    381,    248,   2106,   1433,   2106,    522,    526,   1433 ],
"Category": [ "Default", "Default", "Default", "Default", "Default", "Default", "Default", "Default", "Default", "Default", "Default", "Default", "Default", "Default", "Default", "Default", "Default", "Default", "Default", "Default", "Default", "Default", "Default", "Default", "Default", "Default", "Default", "Default", "Default", "Default", "Topic1", "Topic1", "Topic1", "Topic1", "Topic1", "Topic1", "Topic1", "Topic1", "Topic1", "Topic1", "Topic1", "Topic1", "Topic1", "Topic1", "Topic1", "Topic1", "Topic1", "Topic1", "Topic1", "Topic1", "Topic1", "Topic1", "Topic1", "Topic1", "Topic1", "Topic1", "Topic1", "Topic1", "Topic1", "Topic1", "Topic2", "Topic2", "Topic2", "Topic2", "Topic2", "Topic2", "Topic2", "Topic2", "Topic2", "Topic2", "Topic2", "Topic2", "Topic2", "Topic2", "Topic2", "Topic2", "Topic2", "Topic2", "Topic2", "Topic2", "Topic2", "Topic2", "Topic2", "Topic2", "Topic2", "Topic2", "Topic2", "Topic2", "Topic2", "Topic2", "Topic3", "Topic3", "Topic3", "Topic3", "Topic3", "Topic3", "Topic3", "Topic3", "Topic3", "Topic3", "Topic3", "Topic3", "Topic3", "Topic3", "Topic3", "Topic3", "Topic3", "Topic3", "Topic3", "Topic3", "Topic3", "Topic3", "Topic3", "Topic3", "Topic3", "Topic3", "Topic3", "Topic3", "Topic3", "Topic3", "Topic4", "Topic4", "Topic4", "Topic4", "Topic4", "Topic4", "Topic4", "Topic4", "Topic4", "Topic4", "Topic4", "Topic4", "Topic4", "Topic4", "Topic4", "Topic4", "Topic4", "Topic4", "Topic4", "Topic4", "Topic4", "Topic4", "Topic4", "Topic4", "Topic4", "Topic4", "Topic4", "Topic4", "Topic4", "Topic4", "Topic5", "Topic5", "Topic5", "Topic5", "Topic5", "Topic5", "Topic5", "Topic5", "Topic5", "Topic5", "Topic5", "Topic5", "Topic5", "Topic5", "Topic5", "Topic5", "Topic5", "Topic5", "Topic5", "Topic5", "Topic5", "Topic5", "Topic5", "Topic5", "Topic5", "Topic5", "Topic5", "Topic5", "Topic5", "Topic5", "Topic6", "Topic6", "Topic6", "Topic6", "Topic6", "Topic6", "Topic6", "Topic6", "Topic6", "Topic6", "Topic6", "Topic6", "Topic6", "Topic6", "Topic6", "Topic6", "Topic6", "Topic6", "Topic6", "Topic6", "Topic6", "Topic6", "Topic6", "Topic6", "Topic6", "Topic6", "Topic6", "Topic6", "Topic6", "Topic6", "Topic7", "Topic7", "Topic7", "Topic7", "Topic7", "Topic7", "Topic7", "Topic7", "Topic7", "Topic7", "Topic7", "Topic7", "Topic7", "Topic7", "Topic7", "Topic7", "Topic7", "Topic7", "Topic7", "Topic7", "Topic7", "Topic7", "Topic7", "Topic7", "Topic7", "Topic7", "Topic7", "Topic7", "Topic7", "Topic7", "Topic8", "Topic8", "Topic8", "Topic8", "Topic8", "Topic8", "Topic8", "Topic8", "Topic8", "Topic8", "Topic8", "Topic8", "Topic8", "Topic8", "Topic8", "Topic8", "Topic8", "Topic8", "Topic8", "Topic8", "Topic8", "Topic8", "Topic8", "Topic8", "Topic8", "Topic8", "Topic8", "Topic8", "Topic8", "Topic8", "Topic1", "Topic1", "Topic1", "Topic1", "Topic1", "Topic1", "Topic1", "Topic1", "Topic1", "Topic1", "Topic1", "Topic1", "Topic1", "Topic1", "Topic1", "Topic1", "Topic1", "Topic1", "Topic1", "Topic2", "Topic2", "Topic2", "Topic2", "Topic2", "Topic2", "Topic2", "Topic2", "Topic2", "Topic2", "Topic2", "Topic3", "Topic3", "Topic3", "Topic3", "Topic3", "Topic3", "Topic3", "Topic3", "Topic3", "Topic3", "Topic3", "Topic3", "Topic4", "Topic4", "Topic4", "Topic4", "Topic4", "Topic4", "Topic4", "Topic4", "Topic5", "Topic5", "Topic5", "Topic5", "Topic5", "Topic5", "Topic5", "Topic6", "Topic6", "Topic6", "Topic6", "Topic6", "Topic6", "Topic6", "Topic6", "Topic6", "Topic6", "Topic6", "Topic6", "Topic6", "Topic7", "Topic7", "Topic7", "Topic7", "Topic7", "Topic7", "Topic7", "Topic7", "Topic8", "Topic8", "Topic8", "Topic8", "Topic8", "Topic1", "Topic1", "Topic1", "Topic5", "Topic4", "Topic8", "Topic2", "Topic3", "Topic7", "Topic2", "Topic3", "Topic7", "Topic1", "Topic2", "Topic4" ] 
},
"token.table": {
 "Term": [ "2015", "2015", "actually", "actually", "adult", "already", "always", "amazing", "amo", "anyone", "anything", "app", "app", "april", "around", "art", "ask", "ass", "automatically", "awesome", "babe", "baby", "back", "bad", "beautiful", "bed", "best", "better", "big", "birthday", "biscuits", "black", "boy", "brazil", "bruce", "call", "can", "can", "cant", "car", "care", "caught", "cause", "change", "check", "checked", "click", "code", "coffin", "come", "comes", "coming", "couldnt", "couple", "crazy", "cute", "date", "day", "days", "dead", "deals", "didnt", "discount", "doesnt", "done", "dont", "dream", "dress", "drummer", "ebay", "end", "even", "ever", "every", "everyone", "everything", "excited", "face", "facebook", "fake", "fan", "fans", "fav", "feel", "find", "first", "follow", "followback", "followed", "follower", "followers", "following", "followmejosh", "follows", "followtrick", "found", "free", "friday", "friend", "friends", "fuck", "fucking", "full", "fun", "funny", "gain", "game", "gameinsight", "get", "getting", "girl", "girls", "give", "goals", "god", "going", "gold", "gonna", "good", "got", "gotta", "great", "great", "greysanatomy", "guys", "haha", "hair", "hand", "happen", "happy", "happy", "hard", "harry", "hate", "head", "heart", "hello", "help", "heroprinceofpop", "hey", "high", "hii", "history", "hit", "home", "hope", "hope", "hot", "htt", "httptcoxhrka1pcje", "ily", "ilysm", "inside", "ipad", "issue", "jabberduck", "jenner", "job", "join", "josh", "just", "keep", "kids", "know", "last", "laughted", "left", "let", "let", "life", "like", "liked", "little", "live", "lmao", "lol", "long", "look", "look", "looking", "looks", "lot", "lot", "love", "loves", "made", "made", "made", "make", "make", "makes", "making", "man", "man", "many", "mate", "may", "mean", "mean", "media", "mgwv", "mind", "miss", "miss", "miss", "mom", "money", "mood", "morning", "much", "much", "music", "need", "need", "never", "new", "next", "nice", "nigga", "night", "nothing", "now", "nowplaying", "nsfw", "old", "omg", "one", "opens", "pal", "park", "party", "people", "person", "person", "photo", "photo", "place", "play", "please", "please", "pls", "pool", "porn", "post", "posted", "president", "pretty", "profile", "proud", "put", "read", "ready", "real", "really", "relationship", "remember", "retweet", "retweet", "right", "road", "rumor", "sad", "said", "sale", "save", "say", "school", "see", "seen", "senior", "set", "sex", "sexy", "shit", "shot", "shots", "show", "single", "size", "sleep", "smile", "snapchat", "social", "someone", "something", "song", "soon", "sorry", "spread", "start", "stats", "stay", "still", "stop", "story", "support", "sure", "take", "take", "talk", "talking", "teamfollowback", "tell", "text", "texting", "thank", "thanks", "thing", "things", "think", "though", "time", "today", "together", "tomorrow", "tonight", "top", "true", "truth", "try", "trying", "trying", "tweet", "twitter", "two", "understand", "unfollowed", "unfollower", "unfollowers", "use", "via", "video", "video", "vintage", "wait", "waiting", "wanna", "want", "waste", "watch", "watching", "way", "ways", "wear", "weather", "week", "weekend", "will", "win", "wish", "without", "work", "work", "working", "world", "world", "wow", "wrong", "yall", "yeah", "year", "years", "yes", "york" ],
"Topic": [ 1, 6, 1, 7, 1, 7, 8, 5, 2, 8, 4, 5, 6, 1, 6, 4, 4, 6, 5, 6, 2, 2, 3, 4, 5, 8, 7, 7, 1, 4, 1, 1, 6, 2, 7, 2, 2, 4, 2, 6, 4, 7, 4, 3, 6, 5, 3, 1, 7, 3, 3, 3, 3, 7, 6, 1, 6, 5, 2, 6, 6, 7, 1, 4, 3, 4, 2, 1, 2, 1, 3, 7, 7, 3, 3, 8, 5, 6, 5, 4, 8, 8, 1, 7, 7, 3, 2, 2, 5, 5, 5, 2, 2, 2, 2, 5, 8, 6, 7, 3, 4, 1, 1, 3, 2, 2, 8, 6, 6, 1, 4, 1, 8, 7, 8, 7, 6, 5, 2, 7, 2, 3, 4, 8, 6, 5, 1, 8, 8, 2, 4, 6, 2, 4, 7, 7, 2, 8, 6, 2, 1, 2, 7, 6, 4, 2, 4, 6, 7, 7, 2, 2, 7, 6, 6, 1, 7, 1, 8, 2, 5, 1, 5, 4, 6, 7, 6, 3, 4, 3, 7, 8, 1, 6, 2, 4, 3, 3, 7, 7, 7, 2, 7, 2, 2, 1, 5, 6, 2, 5, 8, 7, 1, 7, 3, 4, 1, 2, 7, 8, 2, 2, 1, 2, 4, 1, 4, 1, 2, 2, 7, 6, 1, 4, 3, 5, 6, 4, 2, 6, 4, 5, 6, 1, 1, 1, 5, 5, 4, 5, 6, 4, 5, 7, 4, 5, 7, 1, 2, 8, 2, 6, 1, 5, 5, 1, 3, 6, 2, 4, 1, 6, 1, 4, 7, 8, 2, 8, 5, 8, 8, 8, 1, 1, 3, 4, 1, 3, 8, 3, 6, 7, 1, 1, 6, 5, 6, 5, 1, 8, 6, 3, 8, 3, 3, 5, 3, 3, 8, 3, 5, 3, 7, 4, 3, 8, 3, 2, 3, 6, 4, 2, 4, 3, 1, 8, 6, 3, 8, 8, 7, 3, 5, 7, 8, 2, 1, 2, 4, 4, 3, 6, 8, 6, 1, 4, 5, 5, 5, 1, 5, 7, 8, 1, 2, 3, 3, 4, 4, 5, 6, 7, 3, 1, 1, 6, 3, 8, 8, 4, 3, 1, 3, 6, 7, 8, 5, 4, 7, 1, 4, 7, 1, 5 ],
"Freq": [ 0.99537, 0.0046296, 0.0030303, 0.99697,      1,      1,      1,      1,      1,      1,      1, 0.99517, 0.0048309,      1,      1,      1,      1,      1,      1,      1,      1,      1,      1,      1,      1,      1,      1,      1,      1,      1,      1,      1,      1,      1,      1,      1, 0.0010302, 0.99897,      1,      1,      1,      1,      1,      1,      1,      1,      1,      1,      1,      1,      1,      1,      1,      1,      1,      1,      1,      1,      1,      1,      1,      1,      1,      1,      1,      1,      1,      1,      1,      1,      1,      1,      1,      1,      1,      1,      1,      1,      1,      1,      1,      1,      1,      1,      1,      1,      1,      1,      1,      1,      1,      1,      1,      1,      1,      1,      1,      1,      1,      1,      1,      1,      1,      1,      1,      1,      1,      1,      1,      1,      1,      1,      1,      1,      1,      1,      1,      1,      1,      1,      1, 0.7083, 0.2917,      1,      1,      1,      1,      1,      1, 0.079728, 0.92027,      1,      1,      1,      1,      1,      1,      1,      1,      1,      1,      1,      1,      1,      1, 0.98858, 0.011424,      1,      1,      1,      1,      1,      1,      1,      1,      1,      1,      1,      1,      1,      1,      1,      1,      1,      1,      1,      1, 0.99492, 0.0050847,      1,      1,      1,      1,      1,      1,      1,      1, 0.99886, 0.0011364,      1,      1, 0.65399, 0.34601,      1,      1, 0.99385, 0.0040984, 0.0020492, 0.00050025,  0.999,      1,      1, 0.99728, 0.0027174,      1,      1,      1, 0.0014472, 0.99855,      1,      1,      1, 0.82567, 0.051724, 0.12261,      1,      1,      1,      1, 0.65195, 0.34805,      1, 0.97968, 0.020316,      1,      1,      1,      1,      1,      1,      1,      1,      1,      1,      1,      1,      1,      1,      1,      1,      1,      1, 0.99853, 0.0014663, 0.99372, 0.0062762,      1,      1, 0.98815, 0.011848,      1,      1,      1,      1,      1,      1,      1,      1,      1,      1,      1,      1,      1,      1,      1,      1, 0.94769, 0.052308,      1,      1,      1,      1,      1,      1,      1,      1,      1,      1,      1,      1,      1,      1,      1,      1,      1,      1,      1,      1,      1,      1,      1,      1,      1,      1,      1,      1,      1,      1,      1,      1,      1,      1,      1,      1,      1,      1,      1, 0.0010638, 0.99894,      1,      1,      1,      1,      1,      1,      1,      1,      1,      1,      1,      1,      1,      1,      1,      1,      1,      1,      1,      1,      1, 0.99738, 0.0026247,      1,      1,      1,      1,      1,      1,      1,      1,      1, 0.086331, 0.91367,      1,      1,      1,      1,      1,      1,      1,      1,      1,      1,      1,      1,      1,      1,      1,      1,      1,      1, 0.99536, 0.0046368,      1, 0.003055, 0.99695,      1,      1,      1,      1,      1,      1,      1,      1 ] 
},
"R":     30,
"lambda.step":   0.01,
"plot.opts": {
 "xlab": "PC1",
"ylab": "PC2" 
},
"topic.order": [ 1, 2, 3, 4, 5, 6, 7, 8 ] 
}